excelbird/__init__.py
excelbird/_cli.py
excelbird/_formulae.py
excelbird/_layout_references.py
excelbird/colors.py
excelbird/exceptions.py
excelbird/fn.py
excelbird/formats.py
excelbird/schema.py
excelbird/styles.py
excelbird/_base/__init__.py
excelbird/_base/container.py
excelbird/_base/dotdict.py
excelbird/_base/help.py
excelbird/_base/identifier.py
excelbird/_base/loc.py
excelbird/_base/math.py
excelbird/_base/styling.py
excelbird/_pygments/__init__.py
excelbird/_pygments/abap.py
excelbird/_pygments/algol.py
excelbird/_pygments/algol_nu.py
excelbird/_pygments/arduino.py
excelbird/_pygments/autumn.py
excelbird/_pygments/borland.py
excelbird/_pygments/bw.py
excelbird/_pygments/colorful.py
excelbird/_pygments/dark.py
excelbird/_pygments/default.py
excelbird/_pygments/dracula.py
excelbird/_pygments/emacs.py
excelbird/_pygments/friendly.py
excelbird/_pygments/friendly_grayscale.py
excelbird/_pygments/fruity.py
excelbird/_pygments/gh_dark.py
excelbird/_pygments/gruvbox.py
excelbird/_pygments/igor.py
excelbird/_pygments/inkpot.py
excelbird/_pygments/light.py
excelbird/_pygments/lilypond.py
excelbird/_pygments/lovelace.py
excelbird/_pygments/manni.py
excelbird/_pygments/material.py
excelbird/_pygments/monokai.py
excelbird/_pygments/murphy.py
excelbird/_pygments/native.py
excelbird/_pygments/nord.py
excelbird/_pygments/onedark.py
excelbird/_pygments/paraiso_dark.py
excelbird/_pygments/paraiso_light.py
excelbird/_pygments/pastie.py
excelbird/_pygments/perldoc.py
excelbird/_pygments/rainbow_dash.py
excelbird/_pygments/rrt.py
excelbird/_pygments/sas.py
excelbird/_pygments/solarized.py
excelbird/_pygments/staroffice.py
excelbird/_pygments/stata_dark.py
excelbird/_pygments/stata_light.py
excelbird/_pygments/tango.py
excelbird/_pygments/trac.py
excelbird/_pygments/vim.py
excelbird/_pygments/vs.py
excelbird/_pygments/xcode.py
excelbird/_pygments/zenburn.py
excelbird/_utils/__init__.py
excelbird/_utils/argument_parsing.py
excelbird/_utils/cell_util.py
excelbird-0.0.14.dist-info/LICENSE
excelbird-0.0.14.dist-info/METADATA
excelbird-0.0.14.dist-info/WHEEL
excelbird-0.0.14.dist-info/entry_points.txt
excelbird-0.0.14.dist-info/top_level.txt
excelbird-0.0.14.dist-info/RECORD
